  // access flags 0x9
  public static main([Ljava/lang/String;)V
   L0
    LINENUMBER 33 L0
    INVOKESTATIC scheduler/Scheduler.getScheduler ()Lscheduler/Scheduler;
    ASTORE 1
   L1
    LINENUMBER 37 L1
    INVOKESTATIC java/lang/Thread.currentThread ()Ljava/lang/Thread;
    ASTORE 3
   L2
    LINENUMBER 40 L2
    NEW java/util/ArrayList
    DUP
    INVOKESPECIAL java/util/ArrayList.<init> ()V
    ASTORE 4
   L3
    LINENUMBER 47 L3
    ICONST_0
    ISTORE 6
   L4
    GOTO L5
   L6
    LINENUMBER 49 L6
   FRAME FULL [[Ljava/lang/String; scheduler/Scheduler T java/lang/Thread java/util/ArrayList T I] []
    BIPUSH 65
    ILOAD 6
    IADD
    I2C
    ISTORE 5
   L7
    LINENUMBER 50 L7
    NEW test/TestThread
    DUP
    NEW java/lang/StringBuilder
    DUP
    ILOAD 5
    INVOKESTATIC java/lang/String.valueOf (C)Ljava/lang/String;
    INVOKESPECIAL java/lang/StringBuilder.<init> (Ljava/lang/String;)V
    INVOKEVIRTUAL java/lang/StringBuilder.toString ()Ljava/lang/String;
    INVOKESPECIAL test/TestThread.<init> (Ljava/lang/String;)V
    ASTORE 2
   L8
    LINENUMBER 52 L8
    ALOAD 4
    ALOAD 3
    INVOKEVIRTUAL java/lang/Thread.getName ()Ljava/lang/String;
    INVOKEVIRTUAL java/util/ArrayList.add (Ljava/lang/Object;)Z
    POP
   L9
    LINENUMBER 53 L9
    ALOAD 1
    ALOAD 2
    INVOKEVIRTUAL scheduler/Scheduler.addThread (Ljava/lang/Thread;)V
   L10
    LINENUMBER 54 L10
    ALOAD 2
    INVOKEVIRTUAL java/lang/Thread.start ()V
   L11
    LINENUMBER 55 L11
    ALOAD 2
    INVOKEVIRTUAL java/lang/Thread.suspend ()V
   L12
    LINENUMBER 47 L12
    IINC 6 1
   L5
   FRAME SAME
    ILOAD 6
    ICONST_5
    IF_ICMPLT L6
   L13
    LINENUMBER 59 L13
    RETURN
   L14
    LOCALVARIABLE args [Ljava/lang/String; L0 L14 0
    LOCALVARIABLE sd Lscheduler/Scheduler; L1 L14 1
    LOCALVARIABLE t Ljava/lang/Thread; L8 L5 2
    LOCALVARIABLE threadNow Ljava/lang/Thread; L2 L14 3
    LOCALVARIABLE threadOrderlist Ljava/util/ArrayList; L3 L14 4
    // signature Ljava/util/ArrayList<Ljava/lang/String;>;
    // declaration: java.util.ArrayList<java.lang.String>
    LOCALVARIABLE c C L7 L5 5
    LOCALVARIABLE i I L4 L13 6
    MAXSTACK = 5
    MAXLOCALS = 7
