// access flags 0x1
  public updateData()V
   L0
    LINENUMBER 42 L0
    LDC "record"
    INVOKESTATIC recorder/RecordTable.getRecordTable (Ljava/lang/String;)Lrecorder/RecordTable;
    PUTSTATIC microbench/BenchSharedObject.Retable : Lrecorder/RecordTable;
   L1
    LINENUMBER 43 L1
    LDC "record"
    INVOKESTATIC recorder/RandomTable.getRandomTable (Ljava/lang/String;)Lrecorder/RandomTable;
    PUTSTATIC microbench/BenchSharedObject.Rantable : Lrecorder/RandomTable;
   L2
    LINENUMBER 45 L2
    ACONST_NULL
    ASTORE 1
   L3
    LINENUMBER 47 L3
    ICONST_0
    ISTORE 2
   L4
    LINENUMBER 51 L4
    ALOAD 0
    GETFIELD microbench/BenchSharedObject.r : Ljava/util/Random;
    ALOAD 0
    GETFIELD microbench/BenchSharedObject.size : I
    INVOKEVIRTUAL java/util/Random.nextInt (I)I
    ISTORE 2
   L5
    LINENUMBER 53 L5
    GETSTATIC microbench/BenchSharedObject.Rantable : Lrecorder/RandomTable;
    INVOKESTATIC java/lang/Thread.currentThread ()Ljava/lang/Thread;
    INVOKEVIRTUAL java/lang/Thread.getName ()Ljava/lang/String;
    NEW java/lang/StringBuilder
    DUP
    LDC "__data_"
    INVOKESPECIAL java/lang/StringBuilder.<init> (Ljava/lang/String;)V
    ILOAD 2
    INVOKEVIRTUAL java/lang/StringBuilder.append (I)Ljava/lang/StringBuilder;
    INVOKEVIRTUAL java/lang/StringBuilder.toString ()Ljava/lang/String;
    INVOKEVIRTUAL recorder/RandomTable.record (Ljava/lang/String;Ljava/lang/String;)V
   L6
    LINENUMBER 86 L6
    ILOAD 2
    IFNE L7
   L8
    LINENUMBER 87 L8
    GETSTATIC microbench/BenchSharedObject.__data_0 : I
    ICONST_1
    IADD
    PUTSTATIC microbench/BenchSharedObject.__data_0 : I
   L9
    LINENUMBER 88 L9
    GETSTATIC microbench/BenchSharedObject.Retable : Lrecorder/RecordTable;
    LDC "__data_0"
    INVOKESTATIC java/lang/Thread.currentThread ()Ljava/lang/Thread;
    INVOKEVIRTUAL java/lang/Thread.getName ()Ljava/lang/String;
    INVOKEVIRTUAL recorder/RecordTable.record (Ljava/lang/String;Ljava/lang/String;)V
   L10
    LINENUMBER 89 L10
    GOTO L11
   L7
   FRAME APPEND [java/lang/String I]
    ILOAD 2
    ICONST_1
    IF_ICMPNE L12
   L13
    LINENUMBER 90 L13
    GETSTATIC microbench/BenchSharedObject.__data_1 : I
    ICONST_1
    IADD
    PUTSTATIC microbench/BenchSharedObject.__data_1 : I
   L14
    LINENUMBER 91 L14
    GETSTATIC microbench/BenchSharedObject.Retable : Lrecorder/RecordTable;
    LDC "__data_1"
    INVOKESTATIC java/lang/Thread.currentThread ()Ljava/lang/Thread;
    INVOKEVIRTUAL java/lang/Thread.getName ()Ljava/lang/String;
    INVOKEVIRTUAL recorder/RecordTable.record (Ljava/lang/String;Ljava/lang/String;)V
   L15
    LINENUMBER 92 L15
    GOTO L11
   L12
   FRAME SAME
    ILOAD 2
    ICONST_2
    IF_ICMPNE L16
   L17
    LINENUMBER 93 L17
    GETSTATIC microbench/BenchSharedObject.__data_2 : I
    ICONST_1
    IADD
    PUTSTATIC microbench/BenchSharedObject.__data_2 : I
   L18
    LINENUMBER 94 L18
    GETSTATIC microbench/BenchSharedObject.Retable : Lrecorder/RecordTable;
    LDC "__data_2"
    INVOKESTATIC java/lang/Thread.currentThread ()Ljava/lang/Thread;
    INVOKEVIRTUAL java/lang/Thread.getName ()Ljava/lang/String;
    INVOKEVIRTUAL recorder/RecordTable.record (Ljava/lang/String;Ljava/lang/String;)V
   L19
    LINENUMBER 95 L19
    GOTO L11
   L16
   FRAME SAME
    ILOAD 2
    ICONST_3
    IF_ICMPNE L20
   L21
    LINENUMBER 96 L21
    GETSTATIC microbench/BenchSharedObject.__data_3 : I
    ICONST_1
    IADD
    PUTSTATIC microbench/BenchSharedObject.__data_3 : I
   L22
    LINENUMBER 97 L22
    GETSTATIC microbench/BenchSharedObject.Retable : Lrecorder/RecordTable;
    LDC "__data_3"
    INVOKESTATIC java/lang/Thread.currentThread ()Ljava/lang/Thread;
    INVOKEVIRTUAL java/lang/Thread.getName ()Ljava/lang/String;
    INVOKEVIRTUAL recorder/RecordTable.record (Ljava/lang/String;Ljava/lang/String;)V
   L23
    LINENUMBER 98 L23
    GOTO L11
   L20
   FRAME SAME
    ILOAD 2
    ICONST_4
    IF_ICMPNE L11
   L24
    LINENUMBER 99 L24
    GETSTATIC microbench/BenchSharedObject.__data_4 : I
    ICONST_1
    IADD
    PUTSTATIC microbench/BenchSharedObject.__data_4 : I
   L25
    LINENUMBER 100 L25
    GETSTATIC microbench/BenchSharedObject.Retable : Lrecorder/RecordTable;
    LDC "__data_4"
    INVOKESTATIC java/lang/Thread.currentThread ()Ljava/lang/Thread;
    INVOKEVIRTUAL java/lang/Thread.getName ()Ljava/lang/String;
    INVOKEVIRTUAL recorder/RecordTable.record (Ljava/lang/String;Ljava/lang/String;)V
   L11
    LINENUMBER 121 L11
   FRAME SAME
    RETURN
   L26
    LOCALVARIABLE this Lmicrobench/BenchSharedObject; L0 L26 0
    LOCALVARIABLE index Ljava/lang/String; L3 L26 1
    LOCALVARIABLE ranv I L4 L26 2
    MAXSTACK = 5
    MAXLOCALS = 3
